{
  "project": {
    "name": "Luxury Waterfront Estate",
    "client": "The Johnson Family Trust",
    "address": "15 Oceanview Drive, Malibu, CA 90265",
    "totalBudget": 2850000,
    "status": "planning"
  },
  "trades": {
    "Professional Services": {
      "name": "Professional Services",
      "lineItems": [
        {
          "category": "ARCHITECTURAL DESIGN",
          "vendor": "Coastal Design Associates",
          "budgetAmount": 125000,
          "notes": "Complete architectural plans for luxury waterfront residence"
        },
        {
          "category": "STRUCTURAL ENGINEERING",
          "vendor": "Pacific Structural Engineers",
          "budgetAmount": 45000,
          "notes": "Foundation and structural analysis for coastal construction"
        }
      ]
    },
    "General Conditions": {
      "name": "General Conditions",
      "lineItems": [
        {
          "category": "BUILDING PERMITS",
          "vendor": "Malibu Building Department",
          "budgetAmount": 25000,
          "notes": "All required permits for luxury residential construction"
        },
        {
          "category": "SURVEYS",
          "vendor": "Precision Land Surveyors",
          "budgetAmount": 15000,
          "notes": "Topographic and boundary surveys"
        }
      ]
    },
    "Shell": {
      "name": "Shell",
      "lineItems": [
        {
          "category": "SHELL / ROOF FRAMING L&M",
          "vendor": "Premier Framing Solutions",
          "budgetAmount": 485000,
          "notes": "Premium lumber and steel framing for oceanfront residence"
        }
      ]
    },
    "Plumbing": {
      "name": "Plumbing",
      "lineItems": [
        {
          "category": "ROUGH PLUMBING",
          "vendor": "Elite Plumbing Systems",
          "budgetAmount": 125000,
          "notes": "High-end plumbing rough-in with luxury fixtures preparation"
        }
      ]
    },
    "Electrical & Low Voltage": {
      "name": "Electrical & Low Voltage",
      "lineItems": [
        {
          "category": "ROUGH ELECTRICAL",
          "vendor": "Coastal Electric Contractors",
          "budgetAmount": 185000,
          "notes": "Smart home electrical infrastructure and ocean-rated components"
        }
      ]
    }
  }
}